[
  {
    "title": "rerre",
    "description": "rereer",
    "date": "2023-08-08",
    "id": 94853
  },
  {
    "title": "sdasdasdasda",
    "description": "sadsadsadsdasadsad",
    "date": "2023-08-04",
    "id": 57910
  },
  {
    "title": [
      "sdaddadda"
    ],
    "description": [
      "daddasaaddsasa"
    ],
    "date": [
      "2023-08-24"
    ],
    "image": "/uploads/1692732431085-big.png",
    "id": 66369
  },
  {
    "title": [
      "test"
    ],
    "description": [
      "sAd"
    ],
    "date": [
      "2023-08-24"
    ],
    "image": "/uploads/1692732458665-tr.png",
    "id": 69368
  },
  {
    "title": [
      "TEST "
    ],
    "description": [
      "TEST"
    ],
    "date": [
      "2023-08-05"
    ],
    "image": "/uploads/1692733657892-big.png",
    "id": 84228
  }
]